{
  "service_order": [
    {
      "id": 1,
      "client": "Nancy Gusmão",
      "bike": "Caloi Azul",
      "service": "Revisão",
      "description": "Occaecat commodo aliqua excepteur nisi do proident aute qui magna ad culpa laboris enim duis.",
      "responsible": "Thiago",
      "price": "60",
      "status": "aberto",
      "created_at": "2022-09-10",
      "updated_at": "",
      "active": 1
    },
    {
      "id": 2,
      "bike": "Monark Verde",
      "client": "Maksim Sousa",
      "service": "Conserto",
      "description": "Ut commodo pariatur laboris sit eu consectetur consequat sit velit dolore reprehenderit ipsum.",
      "responsible": "Otávio",
      "price": "120",
      "status": "finalizado",
      "created_at": "2022-09-14",
      "updated_at": "2022-12-03"
    },
    {
      "id": 3,
      "bike": "Sense Vermelho/Verde",
      "client": "Filipa Vilhena",
      "service": "Lavagem",
      "description": "Labore nostrud dolor est nostrud.",
      "responsible": "Thiago",
      "price": "150",
      "status": "finalizado",
      "created_at": "2022-09-20",
      "updated_at": "2022-10-03",
      "active": 1
    },
    {
      "id": 4,
      "client": "Mateo Lucena",
      "bike": "Durban Laranja",
      "service": "Troca de peças",
      "description": "Commodo mollit amet est qui labore mollit reprehenderit nisi incididunt.",
      "responsible": "Otávio",
      "price": "80",
      "status": "finalizado",
      "created_at": "2022-09-14",
      "updated_at": "2022-09-17",
      "active": 1
    },
    {
      "id": 5,
      "client": "Cláudio Campos",
      "bike": "Colli Rosa",
      "service": "Revisão",
      "description": "Velit Lorem occaecat qui esse.",
      "responsible": "Thiago",
      "price": "60",
      "status": "pendente",
      "created_at": "2022-09-24",
      "updated_at": "",
      "active": 1
    },
    {
      "id": 6,
      "bike": "KSW Amarela",
      "client": "Darius Ourique",
      "service": "Revisão",
      "description": "Sint elit minim est ullamco duis aute adipisicing consectetur non irure quis culpa.",
      "responsible": "Thiago",
      "price": "200",
      "status": "aberto",
      "created_at": "2022-09-18",
      "updated_at": "2022-10-03",
      "active": 1
    },
    {
      "id": "8c272499-75be-4737-89b7-2e8639820ea2",
      "bike": "Caloi Amarela",
      "client": "João Silva",
      "service": "Revisão",
      "description": "",
      "responsible": "Otávio",
      "price": "80",
      "status": "aberto",
      "created_at": "2022-10-07",
      "updated_at": "2022-10-07",
      "active": 1
    },
    {
      "id": "205cdd1d-47f3-4625-b45b-a182da82c72f",
      "bike": "KSW Rosa",
      "client": "Maria",
      "service": "Troca de pneu dianteiro",
      "description": "Troca de pneu dianteiro pelo Pirelli",
      "responsible": "Otávio",
      "price": "120",
      "status": "pendente",
      "created_at": "2022-10-07",
      "updated_at": "2022-10-11",
      "active": 1
    },
    {
      "id": "6efdba09-be7c-43a6-a53e-c4a44c7e280f",
      "bike": "Bike Teste",
      "client": "Felipe",
      "service": "Revisão",
      "description": "afcdfc",
      "responsible": "Thiago",
      "price": "120",
      "status": "aberto",
      "created_at": "2022-12-03",
      "updated_at": "2022-12-03",
      "active": 0
    },
    {
      "id": "1748326d-9d5b-4704-9394-27ff4e802462",
      "bike": "KSW Roxa",
      "client": "José Silva",
      "service": "Troca de pneus",
      "description": "Pneu aro 15 amarelo",
      "responsible": "Otávio",
      "price": "150",
      "status": "finalizado",
      "created_at": "2022-12-03",
      "updated_at": "2022-12-03",
      "active": 1
    },
    {
      "id": "00e46980-4370-42ba-a8aa-13ef63ee44bf",
      "bike": "Caloi Azul",
      "client": "Joao Moraes",
      "service": "Revisão completa",
      "description": "pendente de freios",
      "responsible": "Thiago",
      "price": "220",
      "status": "pendente",
      "created_at": "2022-12-03",
      "updated_at": "2022-12-03",
      "active": 0
    },
    {
      "id": "6d81ad4a-a5df-4250-8e8b-6ae844a79bb0",
      "bike": "Colli Preta",
      "client": "Gustavo Duarte",
      "service": "Troca de freios",
      "description": "Freio do cliente não serve, ecomendar outro",
      "responsible": "Leonardo",
      "price": "300",
      "status": "pendente",
      "created_at": "2022-12-03",
      "updated_at": "2022-12-03",
      "active": 0
    },
    {
      "id": "5904b306-1358-46a0-be36-f659587f140f",
      "bike": "KSW Amarela",
      "client": "Joana Nascimento",
      "service": "Lavagem completa",
      "description": "Tirar acessórios antes de lavar",
      "responsible": "Thiago",
      "price": "80",
      "status": "aberto",
      "created_at": "2022-12-03",
      "updated_at": "2022-12-03",
      "active": 0
    },
    {
      "id": "9d11caf8-ce5f-4a83-bfed-be53bb6159ba",
      "bike": "KSW Preta",
      "client": "Gustavo Duarte",
      "service": "Troca de freios",
      "description": "Os freios do cliente não servem, ecomendar outro",
      "responsible": "Leonardo",
      "price": "300",
      "status": "pendente",
      "created_at": "2022-12-03",
      "updated_at": "2022-12-03",
      "active": 0
    },
    {
      "id": "8ad601b0-b94d-4850-ab19-d6f300857c2d",
      "bike": "Colli Rosa",
      "client": "Joana Nascimento",
      "service": "Lavagem completa",
      "description": "Tirar os acessórios antes de lavar",
      "responsible": "Thiago",
      "price": "80",
      "status": "finalizado",
      "created_at": "2022-12-03",
      "updated_at": "2022-12-03",
      "active": 0
    }
  ]
}